circadian/__init__.py
circadian/_modidx.py
circadian/cli.py
circadian/lights.py
circadian/metrics.py
circadian/models.py
circadian/phasetools.py
circadian/plots.py
circadian/prc.py
circadian/readers.py
circadian/sleep.py
circadian/synthetic_data.py
circadian/utils.py
circadian-1.0.3.dist-info/licenses/LICENSE
circadian-1.0.3.dist-info/METADATA
circadian-1.0.3.dist-info/WHEEL
circadian-1.0.3.dist-info/entry_points.txt
circadian-1.0.3.dist-info/top_level.txt
circadian-1.0.3.dist-info/RECORD
